{
  "player_id": 741833,
  "name": "Ángel Cano",
  "position": "Defensa central",
  "date_of_birth": "05/06/1995",
  "nationality": "España",
  "second_nationality": null,
  "height": "1,94 m",
  "foot": "Derecho",
  "squad_number": "5",
  "is_on_loan": 0,
  "market_value": "50mil €Ú",
  "market_value_numeric": 50000,
  "age": 30,
  "birthplace": "Valencia",
  "profile_url": "https://www.transfermarkt.es/angel-cano/profil/spieler/741833",
  "photo_url": "https://img.a.transfermarkt.technology/portrait/header/default.jpg?lm=1",
  "contract_until": "30/06/2026",
  "international_caps": null,
  "agent": "Special Talent",
  "stats": {
    "appearances": 21,
    "goals": 2,
    "assists": 0,
    "yellow_cards": 4,
    "red_cards": 0,
    "minutes_played": 1829
  }
}