{
  "player_id": 100722,
  "name": "Lago Júnior",
  "position": "Extremo izquierdo",
  "date_of_birth": "31/12/1990",
  "nationality": "Costa de Marfil",
  "second_nationality": "España",
  "height": "1,80 m",
  "foot": "Derecho",
  "squad_number": "23",
  "is_on_loan": 0,
  "market_value": "150mil €Ú",
  "market_value_numeric": 150000,
  "age": 35,
  "birthplace": "Yamoussoukro",
  "profile_url": "https://www.transfermarkt.es/lago-junior/profil/spieler/100722",
  "photo_url": "https://img.a.transfermarkt.technology/portrait/header/100722-1583332916.jpg?lm=1",
  "contract_until": "30/06/2026",
  "international_caps": null,
  "agent": "IS SPORTS AGENCY",
  "stats": {
    "appearances": 20,
    "goals": 1,
    "assists": 2,
    "yellow_cards": 2,
    "red_cards": 0,
    "minutes_played": 1110
  }
}