{
  "player_id": 191217,
  "name": "Héctor Bellerín",
  "position": "Lateral derecho",
  "date_of_birth": "19/03/1995",
  "nationality": "España",
  "second_nationality": null,
  "height": "1,78 m",
  "foot": "Derecho",
  "squad_number": "2",
  "is_on_loan": 0,
  "market_value": "2,50mill. €Ú",
  "market_value_numeric": 2500000,
  "age": 30,
  "birthplace": "Badalona",
  "profile_url": "https://www.transfermarkt.es/hector-bellerin/profil/spieler/191217",
  "photo_url": "https://img.a.transfermarkt.technology/portrait/header/191217-1676903202.jpg?lm=1",
  "contract_until": "30/06/2028",
  "international_caps": null,
  "agent": "Goal Management",
  "stats": {
    "appearances": 16,
    "goals": 0,
    "assists": 2,
    "yellow_cards": 1,
    "red_cards": 0,
    "minutes_played": 1081
  }
}