{
  "player_id": 937958,
  "name": "Lamine Yamal",
  "position": "Extremo derecho",
  "date_of_birth": "13/07/2007",
  "nationality": "España",
  "second_nationality": null,
  "height": "1,80 m",
  "foot": "Izquierdo",
  "squad_number": "10",
  "is_on_loan": 0,
  "market_value": "200,00mill. €Ú",
  "market_value_numeric": 200000000,
  "age": 18,
  "birthplace": "Esplugues de ...",
  "profile_url": "https://www.transfermarkt.es/lamine-yamal/profil/spieler/937958",
  "photo_url": "https://img.a.transfermarkt.technology/portrait/header/937958-1746563945.jpg?lm=1",
  "contract_until": "30/06/2031",
  "international_caps": null,
  "agent": "Gestifute",
  "stats": {
    "appearances": 17,
    "goals": 8,
    "assists": 9,
    "yellow_cards": 0,
    "red_cards": 0,
    "minutes_played": 1431
  }
}