{
  "player_id": 1183719,
  "name": "Keyliane Abdallah",
  "position": "Extremo derecho",
  "date_of_birth": "05/04/2006",
  "nationality": "Francia",
  "second_nationality": "Comoras",
  "height": "1,85 m",
  "foot": "Izquierdo",
  "squad_number": null,
  "is_on_loan": 0,
  "market_value": "50mil €Ú",
  "market_value_numeric": 50000,
  "age": 19,
  "birthplace": "Kani-Kéli",
  "profile_url": "https://www.transfermarkt.es/keyliane-abdallah/profil/spieler/1183719",
  "photo_url": "https://img.a.transfermarkt.technology/portrait/header/1183719-1770052012.jpg?lm=1",
  "contract_until": "30/06/2026",
  "international_caps": null,
  "agent": "AS1",
  "stats": null
}