{
  "player_id": 65262,
  "name": "Rubén Martínez",
  "position": "Extremo derecho",
  "date_of_birth": "08/12/1989",
  "nationality": "España",
  "second_nationality": null,
  "height": "1,67 m",
  "foot": "Izquierdo",
  "squad_number": "11",
  "is_on_loan": 0,
  "market_value": "50mil €Ú",
  "market_value_numeric": 50000,
  "age": 36,
  "birthplace": "Mahón",
  "profile_url": "https://www.transfermarkt.es/ruben-martinez/profil/spieler/65262",
  "photo_url": "https://img.a.transfermarkt.technology/portrait/header/65262-1725606025.jpg?lm=1",
  "contract_until": "30/06/2026",
  "international_caps": null,
  "agent": null,
  "stats": {
    "appearances": 14,
    "goals": 1,
    "assists": 0,
    "yellow_cards": 1,
    "red_cards": 0,
    "minutes_played": 266
  }
}