{
  "player_id": 509492,
  "name": "Jagoba Zárraga",
  "position": "Portero",
  "date_of_birth": "04/11/1997",
  "nationality": "España",
  "second_nationality": null,
  "height": "1,88 m",
  "foot": "Derecho",
  "squad_number": "1",
  "is_on_loan": 0,
  "market_value": "150mil €Ú",
  "market_value_numeric": 150000,
  "age": 28,
  "birthplace": "Bilbao",
  "profile_url": "https://www.transfermarkt.es/jagoba-zarraga/profil/spieler/509492",
  "photo_url": "https://img.a.transfermarkt.technology/portrait/header/509492-1727462488.png?lm=1",
  "contract_until": "30/06/2026",
  "international_caps": null,
  "agent": "RyS",
  "stats": {
    "appearances": 18,
    "goals": 0,
    "assists": 2,
    "yellow_cards": 14,
    "red_cards": 0,
    "minutes_played": 10
  }
}