{
  "player_id": 1209711,
  "name": "Asier Berzal",
  "position": "Mediocentro",
  "date_of_birth": "06/01/2006",
  "nationality": "España",
  "second_nationality": null,
  "height": null,
  "foot": null,
  "squad_number": "6",
  "is_on_loan": 1,
  "market_value": "25mil €Ú",
  "market_value_numeric": 25000,
  "age": 20,
  "birthplace": "Lardero",
  "profile_url": "https://www.transfermarkt.es/asier-berzal/profil/spieler/1209711",
  "photo_url": "https://img.a.transfermarkt.technology/portrait/header/default.jpg?lm=1",
  "contract_until": "30/06/2026",
  "international_caps": null,
  "agent": "AS1",
  "stats": {
    "appearances": 17,
    "goals": 0,
    "assists": 0,
    "yellow_cards": 2,
    "red_cards": 0,
    "minutes_played": 418
  }
}