{
  "player_id": 251892,
  "name": "Juan Soriano",
  "position": "Portero",
  "date_of_birth": "23/08/1997",
  "nationality": "España",
  "second_nationality": null,
  "height": "1,85 m",
  "foot": "Derecho",
  "squad_number": "1",
  "is_on_loan": 0,
  "market_value": "1,00mill. €Ú",
  "market_value_numeric": 1000000,
  "age": 28,
  "birthplace": "Benacazón",
  "profile_url": "https://www.transfermarkt.es/juan-soriano/profil/spieler/251892",
  "photo_url": "https://img.a.transfermarkt.technology/portrait/header/251892-1583333927.jpg?lm=1",
  "contract_until": "30/06/2027",
  "international_caps": null,
  "agent": "RR-Soccer Management Agency",
  "stats": {
    "appearances": 23,
    "goals": 0,
    "assists": 0,
    "yellow_cards": 23,
    "red_cards": 0,
    "minutes_played": 8
  }
}