{
  "player_id": 740253,
  "name": "Javi Castro",
  "position": "Defensa central",
  "date_of_birth": "13/09/2000",
  "nationality": "España",
  "second_nationality": null,
  "height": "1,83 m",
  "foot": "Derecho",
  "squad_number": "5",
  "is_on_loan": 0,
  "market_value": "1,80mill. €Ú",
  "market_value_numeric": 1800000,
  "age": 25,
  "birthplace": "Madrid",
  "profile_url": "https://www.transfermarkt.es/javi-castro/profil/spieler/740253",
  "photo_url": "https://img.a.transfermarkt.technology/portrait/header/740253-1702509967.png?lm=1",
  "contract_until": "30/06/2026",
  "international_caps": null,
  "agent": "YOU FIRST",
  "stats": {
    "appearances": 18,
    "goals": 2,
    "assists": 0,
    "yellow_cards": 0,
    "red_cards": 0,
    "minutes_played": 1159
  }
}